dfloat11/__init__.py
dfloat11/decode.ptx
dfloat11/dfloat11.py
dfloat11/dfloat11_utils.py
dfloat11-0.5.0.dist-info/LICENSE
dfloat11-0.5.0.dist-info/METADATA
dfloat11-0.5.0.dist-info/WHEEL
dfloat11-0.5.0.dist-info/top_level.txt
dfloat11-0.5.0.dist-info/RECORD
