Metadata-Version: 2.2
Name: dfloat11
Version: 0.5.0
Summary: DFloat11: Fast and memory-efficient GPU inference for losslessly compressed LLMs and diffusion models
Author: Tianyi Zhang
Requires-Python: >=3.9
License-File: LICENSE
Requires-Dist: accelerate
Requires-Dist: dahuffman==0.4.2
Requires-Dist: huggingface-hub
Requires-Dist: safetensors
Requires-Dist: transformers
Requires-Dist: tqdm
Provides-Extra: cuda11
Requires-Dist: cupy-cuda11x; extra == "cuda11"
Provides-Extra: cuda12
Requires-Dist: cupy-cuda12x; extra == "cuda12"
Dynamic: author
Dynamic: description
Dynamic: description-content-type
Dynamic: provides-extra
Dynamic: requires-dist
Dynamic: requires-python
Dynamic: summary
